{
  "$schema": "https://schemas.wp.org/trunk/block.json",
  "apiVersion": 3,
  "name": "gutenkit-pro/stylish-list",
  "version": "1.0.0",
  "title": "Stylish List",
  "category": "gutenkit",
  "icon": "menu-alt3",
  "keywords": [
    "style",
    "list",
    "info",
    "stylish",
    "feature"
  ],
  "description": "Stylish list block for gutenberg.",
  "example": {
    "preview": true
  },
  "attributes": {
    "blockID": {
      "type": "string"
    },
    "blockClass": {
      "type": "string"
    },
    "blocksCSS": {
      "type": "object"
    },
    "gkitListType": {
      "type": "string",
      "default": "vertical"
    },
    "isUseDivider": {
      "type": "boolean",
      "default": false
    },
    "isUseCounter": {
      "type": "boolean",
      "default": false
    },
    "gkitListCounterStyle": {
      "type": "string",
      "default": "normal"
    },
    "gkitListCounterSuffix": {
      "type": "string",
      "default": "."
    },
    "listItems": {
      "type": "array",
      "default": [
        {
          "listItemTitle": "List Item 1",
          "listItemDescription": "",
          "listItemMediaType": "icon",
          "listItemIcon": {
            "title": "chevron-right",
            "src": "<svg version=\"1.1\" xmlns=\"http://www.w3.org/2000/svg\" width=\"32\" height=\"32\" viewBox=\"0 0 32 32\">\n<title>chevron-right</title>\n<path d=\"M8 32c-0.205 0-0.409-0.078-0.566-0.234-0.312-0.312-0.312-0.819 0-1.131l13.834-13.834-13.834-13.834c-0.312-0.312-0.312-0.819 0-1.131s0.819-0.312 1.131 0l14.4 14.4c0.312 0.312 0.312 0.819 0 1.131l-14.4 14.4c-0.156 0.156-0.361 0.234-0.566 0.234z\"></path>\n</svg>\n"
          },
          "listItemImage": {
            "src": ""
          },
          "showBadge": false,
          "listBadgeText": "PRO",
          "listItemBadge2nd": "NEW",
          "listItemBadge3rd": "UPCOMING",
          "listItemBadgeColor": "",
          "listItemBadge2ndColor": "",
          "listItemBadge3rdColor": "",
          "listItemBadgeBgColor": "",
          "listItemBadge2ndBgColor": "",
          "listItemBadge3rdBgColor": "",
          "listItemLink": "",
          "addParticularStyle": false,
          "addParticulaBgColor": "",
          "addParticularTextColor": "",
          "addParticularBorderColor": "",
          "addParticularIconBgColor": ""
        },
        {
          "listItemTitle": "List Item 2",
          "listItemDescription": "",
          "listItemMediaType": "icon",
          "listItemIcon": {
            "title": "chevron-right",
            "src": "<svg version=\"1.1\" xmlns=\"http://www.w3.org/2000/svg\" width=\"32\" height=\"32\" viewBox=\"0 0 32 32\">\n<title>chevron-right</title>\n<path d=\"M8 32c-0.205 0-0.409-0.078-0.566-0.234-0.312-0.312-0.312-0.819 0-1.131l13.834-13.834-13.834-13.834c-0.312-0.312-0.312-0.819 0-1.131s0.819-0.312 1.131 0l14.4 14.4c0.312 0.312 0.312 0.819 0 1.131l-14.4 14.4c-0.156 0.156-0.361 0.234-0.566 0.234z\"></path>\n</svg>\n"
          },
          "listItemImage": {
            "src": ""
          },
          "showBadge": false,
          "listBadgeText": "PRO",
          "listItemBadge2nd": "NEW",
          "listItemBadge3rd": "UPCOMING",
          "listItemBadgeColor": "",
          "listItemBadge2ndColor": "",
          "listItemBadge3rdColor": "",
          "listItemBadgeBgColor": "",
          "listItemBadge2ndBgColor": "",
          "listItemBadge3rdBgColor": "",
          "listItemLink": "",
          "addParticularStyle": false,
          "addParticulaBgColor": "",
          "addParticularTextColor": "",
          "addParticularBorderColor": "",
          "addParticularIconBgColor": ""
        },
        {
          "listItemTitle": "List Item 3",
          "listItemDescription": "",
          "listItemMediaType": "icon",
          "listItemIcon": {
            "title": "chevron-right",
            "src": "<svg version=\"1.1\" xmlns=\"http://www.w3.org/2000/svg\" width=\"32\" height=\"32\" viewBox=\"0 0 32 32\">\n<title>chevron-right</title>\n<path d=\"M8 32c-0.205 0-0.409-0.078-0.566-0.234-0.312-0.312-0.312-0.819 0-1.131l13.834-13.834-13.834-13.834c-0.312-0.312-0.312-0.819 0-1.131s0.819-0.312 1.131 0l14.4 14.4c0.312 0.312 0.312 0.819 0 1.131l-14.4 14.4c-0.156 0.156-0.361 0.234-0.566 0.234z\"></path>\n</svg>\n"
          },
          "listItemImage": {
            "src": ""
          },
          "showBadge": false,
          "listBadgeText": "PRO",
          "listItemBadge2nd": "NEW",
          "listItemBadge3rd": "UPCOMING",
          "listItemBadgeColor": "",
          "listItemBadge2ndColor": "",
          "listItemBadge3rdColor": "",
          "listItemBadgeBgColor": "",
          "listItemBadge2ndBgColor": "",
          "listItemBadge3rdBgColor": "",
          "listItemLink": "",
          "addParticularStyle": false,
          "addParticulaBgColor": "",
          "addParticularTextColor": "",
          "addParticularBorderColor": "",
          "addParticularIconBgColor": ""
        }
      ],
      "excludeCopy": true
    },
    "gkitChooseHoverStyle": {
      "type": "string",
      "default": "none"
    },
    "isEntranceAnimation": {
      "type": "boolean",
      "default": false
    },
    "animationEffects": {
      "type": "object"
    },
    "commonJustifyContent": {
      "type": "string",
      "default": "start"
    },
    "commonALignItems": {
      "type": "string",
      "default": "flex-start"
    },
    "gkitCommonBackground": {
      "type": "object"
    },
    "gkitListCommonShadow": {
      "type": "object"
    },
    "gkitListCommonBorder": {
      "type": "object"
    },
    "gkitCommonBackgroundHover": {
      "type": "object"
    },
    "gkitListCommonShadowHover": {
      "type": "object"
    },
    "gkitListCommonBorderHover": {
      "type": "object"
    },
    "gkitCommonBorderRadiusDesktop": {
      "type": "object"
    },
    "gkitCommonBorderRadiusTablet": {
      "type": "object"
    },
    "gkitCommonBorderRadiusMobile": {
      "type": "object"
    },
    "gkitCommonBorderRadiusTabletLandscape": {
      "type": "object"
    },
    "gkitCommonBorderRadiusMobileLandscape": {
      "type": "object"
    },
    "gkitCommonBorderRadiusLaptop": {
      "type": "object"
    },
    "gkitCommonBorderRadiusWideScreen": {
      "type": "object"
    },
    "gkitCommonBorderPaddingDesktop": {
      "type": "object"
    },
    "gkitCommonBorderPaddingTablet": {
      "type": "object"
    },
    "gkitCommonBorderPaddingMobile": {
      "type": "object"
    },
    "gkitCommonBorderPaddingTabletLandscape": {
      "type": "object"
    },
    "gkitCommonBorderPaddingMobileLandscape": {
      "type": "object"
    },
    "gkitCommonBorderPaddingLaptop": {
      "type": "object"
    },
    "gkitCommonBorderPaddingWideScreen": {
      "type": "object"
    },
    "gkitCommonBorderMarginDesktop": {
      "type": "object"
    },
    "gkitCommonBorderMarginTablet": {
      "type": "object"
    },
    "gkitCommonBorderMarginMobile": {
      "type": "object"
    },
    "gkitCommonBorderMarginTabletLandscape": {
      "type": "object"
    },
    "gkitCommonBorderMarginMobileLandscape": {
      "type": "object"
    },
    "gkitCommonBorderMarginLaptop": {
      "type": "object"
    },
    "gkitCommonBorderMarginWideScreen": {
      "type": "object"
    },
    "iconJustifyContent": {
      "type": "string",
      "default": "left"
    },
    "gkitIconSize": {
      "type": "object",
      "default": {
        "size": 20,
        "unit": "px"
      }
    },
    "gkitIconSizeDesktop": {
      "type": "object"
    },
    "gkitIconSizeWideScreen": {
      "type": "object"
    },
    "gkitIconSizeLaptop": {
      "type": "object"
    },
    "gkitIconSizeTabletLandscape": {
      "type": "object"
    },
    "gkitIconSizeTablet": {
      "type": "object"
    },
    "gkitIconSizeMobileLandscape": {
      "type": "object"
    },
    "gkitIconSizeMobile": {
      "type": "object"
    },
    "isUseHeightWidth": {
      "type": "boolean",
      "default": false
    },
    "gkitIconWidth": {
      "type": "object"
    },
    "gkitIconWidthDesktop": {
      "type": "object"
    },
    "gkitIconWidthWideScreen": {
      "type": "object"
    },
    "gkitIconWidthLaptop": {
      "type": "object"
    },
    "gkitIconWidthTabletLandscape": {
      "type": "object"
    },
    "gkitIconWidthTablet": {
      "type": "object"
    },
    "gkitIconWidthMobileLandscape": {
      "type": "object"
    },
    "gkitIconWidthMobile": {
      "type": "object"
    },
    "gkitIconHeight": {
      "type": "object"
    },
    "gkitIconHeightDesktop": {
      "type": "object"
    },
    "gkitIconHeightWideScreen": {
      "type": "object"
    },
    "gkitIconHeightLaptop": {
      "type": "object"
    },
    "gkitIconHeightTabletLandscape": {
      "type": "object"
    },
    "gkitIconHeightTablet": {
      "type": "object"
    },
    "gkitIconHeightMobileLandscape": {
      "type": "object"
    },
    "gkitIconHeightMobile": {
      "type": "object"
    },
    "gkitIconColor": {
      "type": "string",
      "default": "#EF0A0A"
    },
    "gkitIconBackground": {
      "type": "object"
    },
    "gkitIconBorder": {
      "type": "object"
    },
    "gkitIconBorderRadius": {
      "type": "object"
    },
    "gkitIconColorHover": {
      "type": "string"
    },
    "gkitIconBackgroundHover": {
      "type": "object"
    },
    "gkitIconBorderHover": {
      "type": "object"
    },
    "gkitIconBorderRadiusHover": {
      "type": "object"
    },
    "gkitIconPaddingDesktop": {
      "type": "object"
    },
    "gkitIconPaddingTablet": {
      "type": "object"
    },
    "gkitIconPaddingMobile": {
      "type": "object"
    },
    "gkitIconPaddingTabletLandscape": {
      "type": "object"
    },
    "gkitIconPaddingMobileLandscape": {
      "type": "object"
    },
    "gkitIconPaddingLaptop": {
      "type": "object"
    },
    "gkitIconPaddingWideScreen": {
      "type": "object"
    },
    "gkitIconMarginDesktop": {
      "type": "object"
    },
    "gkitIconMarginTablet": {
      "type": "object"
    },
    "gkitIconMarginMobile": {
      "type": "object"
    },
    "gkitIconMarginTabletLandscape": {
      "type": "object"
    },
    "gkitIconMarginMobileLandscape": {
      "type": "object"
    },
    "gkitIconMarginLaptop": {
      "type": "object"
    },
    "gkitIconMarginWideScreen": {
      "type": "object"
    },
    "gkitTitleColor": {
      "type": "string"
    },
    "gkitStrokeColor": {
      "type": "string"
    },
    "gkitTextStrokeWidthDesktop": {
      "type": "object"
    },
    "gkitTextStrokeWidthTablet": {
      "type": "object"
    },
    "gkitTextStrokeWidthMobile": {
      "type": "object"
    },
    "gkitTextStrokeWidthTabletLandscape": {
      "type": "object"
    },
    "gkitTextStrokeWidthMobileLandscape": {
      "type": "object"
    },
    "gkitTextStrokeWidthLaptop": {
      "type": "object"
    },
    "gkitTextStrokeWidthWideScreen": {
      "type": "object"
    },
    "gkitTitleTypography": {
      "type": "object"
    },
    "gkitTitleColorHover": {
      "type": "string",
      "default": "#EF0A0A"
    },
    "gkitTitleTypographyHover": {
      "type": "object"
    },
    "gkitTitleMarginDesktop": {
      "type": "object"
    },
    "gkitTitleMarginTablet": {
      "type": "object"
    },
    "gkitTitleMarginMobile": {
      "type": "object"
    },
    "gkitTitleMarginTabletLandscape": {
      "type": "object"
    },
    "gkitTitleMarginMobileLandscape": {
      "type": "object"
    },
    "gkitTitleMarginLaptop": {
      "type": "object"
    },
    "gkitTitleMarginWideScreen": {
      "type": "object"
    },
    "gkitDescriptionDir": {
      "type": "string",
      "default": "bottom"
    },
    "gkitDescriptionColor": {
      "type": "string"
    },
    "gkitDescriptionColorHover": {
      "type": "string"
    },
    "gkitDescriptionTypography": {
      "type": "object"
    },
    "gkitDescriptionMarginDesktop": {
      "type": "object"
    },
    "gkitDescriptionMarginTablet": {
      "type": "object"
    },
    "gkitDescriptionMarginMobile": {
      "type": "object"
    },
    "gkitDescriptionMarginTabletLandscape": {
      "type": "object"
    },
    "gkitDescriptionMarginMobileLandscape": {
      "type": "object"
    },
    "gkitDescriptionMarginLaptop": {
      "type": "object"
    },
    "gkitDescriptionMarginWideScreen": {
      "type": "object"
    },
    "gkitBadgeDirection": {
      "type": "string",
      "default": "right"
    },
    "gkitBadgeColor": {
      "type": "string",
      "default": "#fff"
    },
    "gkitBadgeBackground": {
      "type": "object"
    },
    "gkitBadgeTypography": {
      "type": "object"
    },
    "gkitBadgeBoxShadow": {
      "type": "object"
    },
    "gkitBadgeBorder": {
      "type": "object"
    },
    "gkitBadgeBorderRadius": {
      "type": "object"
    },
    "gkitBadgePaddingDesktop": {
      "type": "object",
      "default": {
        "top": "2px",
        "right": "5px",
        "bottom": "2px",
        "left": "5px"
      }
    },
    "gkitBadgePaddingTablet": {
      "type": "object"
    },
    "gkitBadgePaddingMobile": {
      "type": "object"
    },
    "gkitBadgePaddingTabletLandscape": {
      "type": "object"
    },
    "gkitBadgePaddingMobileLandscape": {
      "type": "object"
    },
    "gkitBadgePaddingLaptop": {
      "type": "object"
    },
    "gkitBadgePaddingWideScreen": {
      "type": "object"
    },
    "gkitBadgeMarginDesktop": {
      "type": "object"
    },
    "gkitBadgeMarginTablet": {
      "type": "object"
    },
    "gkitBadgeMarginMobile": {
      "type": "object"
    },
    "gkitBadgeMarginTabletLandscape": {
      "type": "object"
    },
    "gkitBadgeMarginMobileLandscape": {
      "type": "object"
    },
    "gkitBadgeMarginLaptop": {
      "type": "object"
    },
    "gkitBadgeMarginWideScreen": {
      "type": "object"
    },
    "gkitCounterDirection": {
      "type": "string",
      "default": "left"
    },
    "gkitCounterColor": {
      "type": "string"
    },
    "gkitCounterColorHover": {
      "type": "string"
    },
    "gkitCounterTypography": {
      "type": "object"
    },
    "gkitCounterMarginDesktop": {
      "type": "object"
    },
    "gkitCounterMarginTablet": {
      "type": "object"
    },
    "gkitCounterMarginMobile": {
      "type": "object"
    },
    "gkitCounterMarginTabletLandscape": {
      "type": "object"
    },
    "gkitCounterMarginMobileLandscape": {
      "type": "object"
    },
    "gkitCounterMarginLaptop": {
      "type": "object"
    },
    "gkitCounterMarginWideScreen": {
      "type": "object"
    },
    "gkitDividerColor": {
      "type": "string",
      "default": "#E6E7EC"
    },
    "gkitDividerType": {
      "type": "string",
      "default": "solid"
    },
    "gkitDividerWidth": {
      "type": "object",
      "default": {
        "size": 100,
        "unit": "%"
      }
    },
    "gkitDividerHeight": {
      "type": "object",
      "default": {
        "size": 1,
        "unit": "px"
      }
    },
    "gkitDividerMarginDesktop": {
      "type": "object"
    },
    "gkitDividerMarginTablet": {
      "type": "object"
    },
    "gkitDividerMarginMobile": {
      "type": "object"
    },
    "gkitDividerMarginTabletLandscape": {
      "type": "object"
    },
    "gkitDividerMarginMobileLandscape": {
      "type": "object"
    },
    "gkitDividerMarginLaptop": {
      "type": "object"
    },
    "gkitDividerMarginWideScreen": {
      "type": "object"
    }
  },
  "providesContext": {
    "gutenkit-pro/isUseCounter": "isUseCounter",
    "gutenkit-pro/isUseDivider": "isUseDivider",
    "gutenkit-pro/gkitListType": "gkitListType"
  },
  "supports": {
    "html": false,
    "align": [
      "wide",
      "full"
    ],
    "anchor": true
  },
  "textdomain": "gutenkit-blocks-addon-pro",
  "editorScript": "file:./index.js",
  "editorStyle": [
    "file:./index.css"
  ],
  "style": [
    "file:./style-index.css"
  ]
}